README.md
setup.py
timeitd.py
timeitd.egg-info/PKG-INFO
timeitd.egg-info/SOURCES.txt
timeitd.egg-info/dependency_links.txt
timeitd.egg-info/not-zip-safe
timeitd.egg-info/top_level.txt