Metadata-Version: 1.1
Name: timeitd
Version: 1.0
Summary: Simple timeit decorator for benchmark functions
Home-page: https://github.com/canercidam/timeitd
Author: Caner Çıdam
Author-email: UNKNOWN
License: MIT
Platform: UNKNOWN
Classifier: License :: OSI Approved :: MIT License
Classifier: Programming Language :: Python
